fold/__init__.py
fold/base/__init__.py
fold/base/classes.py
fold/base/scoring.py
fold/base/utils.py
fold/composites/__init__.py
fold/composites/columns.py
fold/composites/concat.py
fold/composites/ensemble.py
fold/composites/metalabeling.py
fold/composites/metalabeling_strategy.py
fold/composites/residual.py
fold/composites/sample.py
fold/composites/selectbest.py
fold/composites/target.py
fold/composites/utils.py
fold/events/__init__.py
fold/events/filters/__init__.py
fold/events/filters/everynth.py
fold/events/filters/no.py
fold/events/labeling/__init__.py
fold/events/labeling/fixed.py
fold/events/labeling/strategies.py
fold/events/utils.py
fold/events/weights/__init__.py
fold/events/weights/max.py
fold/loop/__init__.py
fold/loop/backend/__init__.py
fold/loop/backend/joblib.py
fold/loop/backend/pathos.py
fold/loop/backend/ray.py
fold/loop/backend/sequential.py
fold/loop/backend/thread.py
fold/loop/backtesting.py
fold/loop/checks.py
fold/loop/common.py
fold/loop/encase.py
fold/loop/inference.py
fold/loop/process/__init__.py
fold/loop/process/process_minibatch.py
fold/loop/training.py
fold/loop/types.py
fold/loop/utils.py
fold/loop/wrap.py
fold/models/__init__.py
fold/models/base.py
fold/models/dummy.py
fold/models/random.py
fold/models/sklearn.py
fold/models/wrappers/__init__.py
fold/models/wrappers/convenience.py
fold/models/wrappers/gbd.py
fold/models/wrappers/types.py
fold/py.typed
fold/splitters.py
fold/transformations/__init__.py
fold/transformations/columns.py
fold/transformations/date.py
fold/transformations/dev.py
fold/transformations/difference.py
fold/transformations/features.py
fold/transformations/function.py
fold/transformations/holidays.py
fold/transformations/lags.py
fold/transformations/math.py
fold/transformations/scaling.py
fold/transformations/sklearn.py
fold/transformations/types.py
fold/utils/__init__.py
fold/utils/checks.py
fold/utils/dataframe.py
fold/utils/dataset.py
fold/utils/forward.py
fold/utils/functional.py
fold/utils/list.py
fold_core-2.0.1.dist-info/LICENSE
fold_core-2.0.1.dist-info/METADATA
fold_core-2.0.1.dist-info/WHEEL
fold_core-2.0.1.dist-info/RECORD
