Metadata-Version: 2.1
Name: fold-core
Version: 2.0.1
Summary: A Time Series Cross-Validation library that lets you build, deploy and update composite models easily. An order of magnitude speed-up, combined with flexibility and rigour.
License: Proprietary
Keywords: time-series,machine-learning,forecasting,forecast,nowcast,models,time-series-regression,time-series-classification,financial-machine-learning
Author: Mark Aron Szulyovszky
Requires-Python: >=3.11,<4.0
Classifier: Development Status :: 5 - Production/Stable
Classifier: License :: Other/Proprietary License
Classifier: Operating System :: OS Independent
Classifier: Programming Language :: Python
Classifier: Programming Language :: Python :: 3
Classifier: Programming Language :: Python :: 3.11
Classifier: Programming Language :: Python :: 3.12
Classifier: Programming Language :: Python :: Implementation :: CPython
Classifier: Programming Language :: Python :: Implementation :: PyPy
Provides-Extra: all
Provides-Extra: arch
Provides-Extra: docs
Provides-Extra: lightgbm
Provides-Extra: prophet
Provides-Extra: quality
Provides-Extra: ray
Provides-Extra: sktime
Provides-Extra: statsforecast
Provides-Extra: statsmodels
Provides-Extra: tests
Provides-Extra: xgboost
Requires-Dist: deepmerge (>=1.0.0)
Requires-Dist: finml-utils (>=2.1)
Requires-Dist: holidays (>=0.10) ; extra == "tests" or extra == "all"
Requires-Dist: image (>=1.5.33) ; extra == "docs"
Requires-Dist: imbalanced-learn (>=0.11.0) ; extra == "tests"
Requires-Dist: iteration_utilities (>=0.11)
Requires-Dist: krisi (>=1.3.0) ; extra == "tests" or extra == "all"
Requires-Dist: lightgbm (>=3.2.1) ; extra == "lightgbm"
Requires-Dist: mkdocs (>=1.2)
Requires-Dist: mkdocs-autorefs (>=0.4) ; extra == "docs"
Requires-Dist: mkdocs-gallery (>=0.7) ; extra == "docs"
Requires-Dist: mkdocs-glightbox (<=0.3.2) ; extra == "docs"
Requires-Dist: mkdocs-include-markdown-plugin (>=4.0) ; extra == "docs"
Requires-Dist: mkdocs-jupyter (>=0.22) ; extra == "docs"
Requires-Dist: mkdocs-material (>=9.0.0) ; extra == "docs"
Requires-Dist: mkdocstrings-python (>=0.9.0) ; extra == "docs"
Requires-Dist: numpy (>=1.16)
Requires-Dist: p_tqdm (>=1.3) ; extra == "all"
Requires-Dist: pandas (>=2.0)
Requires-Dist: pandas_market_calendars (>=4.1.4) ; extra == "tests" or extra == "all"
Requires-Dist: pre-commit (>=2.20.0,<2.21.0) ; extra == "quality"
Requires-Dist: pyarrow (>=2.0) ; extra == "tests"
Requires-Dist: pytest (>=7.1.2,<7.2.0) ; extra == "tests"
Requires-Dist: pytest-cov (>=4.0) ; extra == "tests"
Requires-Dist: ray (>=1.4) ; extra == "ray" or extra == "all"
Requires-Dist: scikit-learn (>=1.4)
Requires-Dist: statsmodels (>=0.12.1) ; extra == "tests" or extra == "all" or extra == "statsmodels"
Requires-Dist: tqdm (>=4.0)
Requires-Dist: typing_extensions (>=4.4.0)
